kombine/__init__.py
kombine/clustered_kde.py
kombine/interruptible_pool.py
kombine/sampler.py
kombine/serialpool.py
kombine/tests.py
kombine/utils.py
kombine-0.8.4.dist-info/AUTHORS.rst
kombine-0.8.4.dist-info/LICENSE
kombine-0.8.4.dist-info/METADATA
kombine-0.8.4.dist-info/WHEEL
kombine-0.8.4.dist-info/top_level.txt
kombine-0.8.4.dist-info/RECORD
