Metadata-Version: 2.1
Name: kombine
Version: 0.8.4
Summary: An embarrassingly parallel, kernel-density-based                 ensemble sampler
Home-page: https://github.com/bfarr/kombine
Author: Ben Farr
Author-email: farr@uchicago.edu
License: UNKNOWN
Platform: UNKNOWN
Classifier: Development Status :: 4 - Beta
Classifier: Programming Language :: Python
Classifier: Programming Language :: Python :: 2
Classifier: Programming Language :: Python :: 2.7
Classifier: Programming Language :: Python :: 3
Classifier: Programming Language :: Python :: 3.4
Classifier: Programming Language :: Python :: 3.5
Classifier: Programming Language :: Python :: 3.6
Classifier: License :: OSI Approved :: MIT License
Requires-Python: >=2.7,!=3.0.*,!=3.1.*,!=3.2.*,!=3.3.*
Requires-Dist: numpy
Requires-Dist: scipy
